README.md
setup.py
ptinnls/__init__.py
ptinnls/methods.py
ptinnls.egg-info/PKG-INFO
ptinnls.egg-info/SOURCES.txt
ptinnls.egg-info/dependency_links.txt
ptinnls.egg-info/requires.txt
ptinnls.egg-info/top_level.txt
tests/test_methods.py