Metadata-Version: 2.4
Name: ptinnls
Version: 0.1.0
Summary: Implements Sparse NNLS
Author: Nathan Wamsley
Author-email: nwamsley@parallelsq.org
Classifier: License :: OSI Approved :: MIT License
Classifier: Programming Language :: Python :: 3
Requires-Python: >=3.6
Requires-Dist: numpy
Requires-Dist: cvxopt
Requires-Dist: scipy
Dynamic: author
Dynamic: author-email
Dynamic: classifier
Dynamic: requires-dist
Dynamic: requires-python
Dynamic: summary
